MVPanalytics/__init__.py
MVPanalytics/analysis.py
MVPanalytics/graphics.py
MVPanalytics/keitaro.py
mvpanalytics-0.1.28.dist-info/METADATA
mvpanalytics-0.1.28.dist-info/WHEEL
mvpanalytics-0.1.28.dist-info/licenses/LICENSE
mvpanalytics-0.1.28.dist-info/RECORD
