Metadata-Version: 2.4
Name: MVPanalytics
Version: 0.1.28
Author-email: "Kirill_Morozov(tu1try)" <kirmorozo6@gmail.com>
License-File: LICENSE
Classifier: License :: OSI Approved :: MIT License
Classifier: Operating System :: OS Independent
Classifier: Programming Language :: Python :: 3
Requires-Python: >=3.9.0
